pyanasolution/__init__.py
pyanasolution/_solution_base.py
pyanasolution/cd_irregular.py
pyanasolution/channel_cos_flow.py
pyanasolution/convection_3d.py
pyanasolution/diffusion_3d.py
pyanasolution/fracture_flow_1d.py
pyanasolution/fracture_thermal_flow.py
pyanasolution/gaussian_hill_2d.py
pyanasolution/gaussian_hill_3d.py
pyanasolution/poiseuille_flow.py
pyanasolution/reinjection_1d.py
pyanasolution/reinjection_2d.py
pyanasolution/semi_infinite_flow_1d.py
pyanasolution/theis.py
pyanasolution/uniform_flow.py
pyanasolution-0.1.9.dist-info/LICENSE
pyanasolution-0.1.9.dist-info/METADATA
pyanasolution-0.1.9.dist-info/WHEEL
pyanasolution-0.1.9.dist-info/top_level.txt
pyanasolution-0.1.9.dist-info/RECORD
