Metadata-Version: 2.1
Name: pyanasolution
Version: 0.1.9
Summary: A calculation tool for common analytical solutions.
Home-page: https://gitee.com/geo-tech/py-ana-solution
Author: P. Hong & F.Y. Zhao
Author-email: frankhp@163.com
Requires-Python: >=3.6
License-File: LICENSE
Requires-Dist: numpy (>=1.18.0)
Requires-Dist: scipy (>=1.10.1)
